clearskies_slack/__init__.py
clearskies_slack/backends/__init__.py
clearskies_slack/backends/message_backend.py
clearskies_slack/backends/slack_backend.py
clearskies_slack/models/__init__.py
clearskies_slack/models/channel.py
clearskies_slack/models/message.py
clear_skies_slack-0.9.1.dist-info/LICENSE
clear_skies_slack-0.9.1.dist-info/METADATA
clear_skies_slack-0.9.1.dist-info/WHEEL
clear_skies_slack-0.9.1.dist-info/RECORD
