Metadata-Version: 2.1
Name: clear-skies-slack
Version: 0.9.1
Summary: clearskies bindings for Slack
Home-page: https://github.com/cmancone/clearskies-slack
License: MIT
Author: Conor Mancone
Author-email: cmancone@gmail.com
Requires-Python: >=3.8,<4.0
Classifier: License :: OSI Approved :: MIT License
Classifier: Programming Language :: Python :: 3
Classifier: Programming Language :: Python :: 3.8
Classifier: Programming Language :: Python :: 3.9
Classifier: Programming Language :: Python :: 3.10
Classifier: Programming Language :: Python :: 3.11
Requires-Dist: clear-skies (>=1.14.4,<2.0.0)
Project-URL: Repository, https://github.com/cmancone/clearskies-slack
